.env
torbot/main.py
torbot/modules/__init__.py
torbot/modules/api.py
torbot/modules/color.py
torbot/modules/config.py
torbot/modules/info.py
torbot/modules/linktree.py
torbot/modules/nlp/README.md
torbot/modules/nlp/__init__.py
torbot/modules/nlp/gather_data.py
torbot/modules/nlp/main.py
torbot/modules/nlp/website_classification.csv
torbot/modules/tests/TESTING.md
torbot/modules/tests/__init__.py
torbot/modules/updater.py
torbot-4.0.0.dist-info/LICENSE.md
torbot-4.0.0.dist-info/METADATA
torbot-4.0.0.dist-info/WHEEL
torbot-4.0.0.dist-info/RECORD
