Metadata-Version: 2.1
Name: torbot
Version: 4.0.0
Summary: OSINT for the dark web
License: GNU GPL
Author: Akeem King
Author-email: akeemtlking@gmail.com
Requires-Python: >=3.9,<=3.11.4
Classifier: License :: Other/Proprietary License
Classifier: Programming Language :: Python :: 3
Classifier: Programming Language :: Python :: 3.9
Classifier: Programming Language :: Python :: 3.10
Classifier: Programming Language :: Python :: 3.11
Requires-Dist: PySocks (==1.7.1)
Requires-Dist: altgraph (==0.17.2)
Requires-Dist: beautifulsoup4 (==4.11.1)
Requires-Dist: certifi (==2023.7.22)
Requires-Dist: charset-normalizer (==2.0.12)
Requires-Dist: decorator (==5.1.1)
Requires-Dist: httpx[socks] (>=0.25.0,<0.26.0)
Requires-Dist: idna (==3.3)
Requires-Dist: igraph (==0.10.6)
Requires-Dist: joblib (==1.2.0)
Requires-Dist: macholib (==1.16)
Requires-Dist: numpy (==1.24.4)
Requires-Dist: phonenumbers (>=8.13.22,<9.0.0)
Requires-Dist: progress (==1.6)
Requires-Dist: pyinstaller (==5.13.0)
Requires-Dist: pyinstaller-hooks-contrib (==2022.7)
Requires-Dist: python-dotenv (==0.20.0)
Requires-Dist: scikit-learn (==1.3.0)
Requires-Dist: scipy (==1.10.0)
Requires-Dist: six (==1.16.0)
Requires-Dist: sklearn (==0.0)
Requires-Dist: soupsieve (==2.3.2.post1)
Requires-Dist: tabulate (>=0.9.0,<0.10.0)
Requires-Dist: termcolor (==1.1.0)
Requires-Dist: texttable (==1.6.4)
Requires-Dist: threadpoolctl (==3.1.0)
Requires-Dist: treelib (>=1.6.1,<2.0.0)
Requires-Dist: unipath (>=1.1,<2.0)
Requires-Dist: urllib3 (==1.26.17)
Requires-Dist: validators (==0.20.0)
Requires-Dist: yattag (==1.14.0)
